gluestick/__init__.py
gluestick/etl_utils.py
gluestick/pandas_utils.py
gluestick/reader.py
gluestick/singer.py
gluestick/readers/__init__.py
gluestick/readers/pl_lazyframe_reader.py
gluestick/readers/pl_reader.py
gluestick/utils/__init__.py
gluestick/utils/polars_utils.py
gluestick-3.0.3.dist-info/licenses/LICENSE
gluestick-3.0.3.dist-info/METADATA
gluestick-3.0.3.dist-info/WHEEL
gluestick-3.0.3.dist-info/top_level.txt
gluestick-3.0.3.dist-info/RECORD
