Metadata-Version: 2.4
Name: gluestick
Version: 3.0.3
Summary: ETL utility functions built for the hotglue iPaaS platform
Home-page: https://github.com/hotgluexyz/gluestick
Author: hotglue
Author-email: hello@hotglue.xyz
License: MIT
License-File: LICENSE
Requires-Dist: singer-python>=4.0.0
Requires-Dist: numpy>=1.4
Requires-Dist: pandas>=1.2.5
Requires-Dist: pyarrow>=8.0.0
Requires-Dist: pytz>=2022.6
Requires-Dist: polars==1.34.0
Dynamic: author
Dynamic: author-email
Dynamic: description
Dynamic: description-content-type
Dynamic: home-page
Dynamic: license
Dynamic: license-file
Dynamic: requires-dist
Dynamic: summary
